thehellmaker_lib_2/__init__.py
thehellmaker_lib_2/main.py
thehellmaker_lib_2-0.1.0.dist-info/METADATA
thehellmaker_lib_2-0.1.0.dist-info/WHEEL
thehellmaker_lib_2-0.1.0.dist-info/RECORD
