Metadata-Version: 2.4
Name: thehellmaker-lib-2
Version: 0.1.0
Summary: Add your description here
Requires-Python: >=3.12.3
Requires-Dist: thehellmaker-lib-1==0.1.3
